vibemark/__init__.py
vibemark/cli.py
vibemark-1.2.1.dist-info/WHEEL
vibemark-1.2.1.dist-info/entry_points.txt
vibemark-1.2.1.dist-info/METADATA
vibemark-1.2.1.dist-info/RECORD
