Metadata-Version: 2.3
Name: vibemark
Version: 1.2.1
Summary: If you are not writing it, you should at least read it.
Author: menisadi
Author-email: menisadi <menisadi@gmail.com>
License: MIT License
Requires-Dist: rich>=14.2.0
Requires-Dist: typer>=0.21.0
Requires-Python: >=3.13
